zyloadmin/__init__.py
zyloadmin/main.py
zylo_admin-1.0.3.dist-info/METADATA
zylo_admin-1.0.3.dist-info/WHEEL
zylo_admin-1.0.3.dist-info/entry_points.txt
zylo_admin-1.0.3.dist-info/top_level.txt
zylo_admin-1.0.3.dist-info/RECORD
