Metadata-Version: 2.1
Name: zylo-admin
Version: 1.0.3
Summary: A battery startup for zylo web framework
Home-page: https://github.com/embracke/zyloadmin
Author: Pawan kumar
Author-email: control@vvfin.in
Classifier: Development Status :: 5 - Production/Stable
Classifier: License :: OSI Approved :: MIT License
Classifier: Programming Language :: Python :: 3
Classifier: Programming Language :: Python :: 3.6
Classifier: Programming Language :: Python :: 3.7
Classifier: Programming Language :: Python :: 3.8
Classifier: Programming Language :: Python :: 3.9
Requires-Dist: zylo
